colabfold/__init__.py
colabfold/alphafold/__init__.py
colabfold/alphafold/models.py
colabfold/alphafold/msa.py
colabfold/batch.py
colabfold/citations.py
colabfold/colabfold.py
colabfold/download.py
colabfold/mmseqs/__init__.py
colabfold/mmseqs/merge_and_split_msas.py
colabfold/mmseqs/search.py
colabfold/mmseqs/split_msas.py
colabfold/openstructure/LGPL.txt
colabfold/openstructure/README.md
colabfold/openstructure/stereo_chemical_props.txt
colabfold/pdb.py
colabfold/plot.py
colabfold/relax.py
colabfold/utils.py
colabfold-1.5.5.dist-info/LICENSE
colabfold-1.5.5.dist-info/METADATA
colabfold-1.5.5.dist-info/WHEEL
colabfold-1.5.5.dist-info/entry_points.txt
colabfold-1.5.5.dist-info/RECORD
